strio/__init__.py
strio/core.py
strio/tests/__init__.py
strio/tests/test_core.py
strio-0.1.0.dist-info/METADATA
strio-0.1.0.dist-info/WHEEL
strio-0.1.0.dist-info/top_level.txt
strio-0.1.0.dist-info/RECORD
